xlhdnumpy/__init__.py
xlhdnumpy/array.py
xlhdnumpy/operations.py
xlhdnumpy-0.3.0.dist-info/METADATA
xlhdnumpy-0.3.0.dist-info/WHEEL
xlhdnumpy-0.3.0.dist-info/top_level.txt
xlhdnumpy-0.3.0.dist-info/RECORD
