Metadata-Version: 2.4
Name: xlhdnumpy
Version: 0.3.0
Summary: A simple numpy-like library for array operations
Home-page: https://github.com/xiaolihuidao/xlhdnumpy
Author: xiaolihuidao
Author-email: cd101168@qq.com
Classifier: Programming Language :: Python :: 3
Classifier: Operating System :: OS Independent
Requires-Python: >=3.8
